pyCoilGenUtils/__init__.py
pyCoilGenUtils/stl_asc2bin.py
pycoilgen_utils-0.0.2.dist-info/entry_points.txt
pycoilgen_utils-0.0.2.dist-info/LICENSE.txt
pycoilgen_utils-0.0.2.dist-info/WHEEL
pycoilgen_utils-0.0.2.dist-info/METADATA
pycoilgen_utils-0.0.2.dist-info/RECORD
