Metadata-Version: 2.1
Name: pycoilgen_utils
Version: 0.0.2
Summary: Extra utilities for pyCoilGen, the Open Source Magnetic Resonance Coil Generator.
Keywords: Utility,STL
Author-email: Kevin Meyer <kevin@kmz.co.za>
Requires-Python: >=3.6
Classifier: Development Status :: 5 - Production/Stable
Classifier: Environment :: Console
Classifier: Intended Audience :: Developers
Classifier: Intended Audience :: Healthcare Industry
Classifier: Intended Audience :: Science/Research
Classifier: License :: OSI Approved :: GNU General Public License v3 or later (GPLv3+)
Classifier: Operating System :: OS Independent
Classifier: Programming Language :: Python
Classifier: Programming Language :: Python :: 3 :: Only
Classifier: Programming Language :: Python :: 3.6
Classifier: Programming Language :: Python :: 3.7
Classifier: Programming Language :: Python :: 3.8
Classifier: Programming Language :: Python :: 3.9
Classifier: Programming Language :: Python :: 3.10
Classifier: Programming Language :: Python :: 3.11
Classifier: Topic :: Scientific/Engineering
Project-URL: Bug tracker, https://github.com/kev-m/pyCoilGen/issues
Project-URL: Changelog, https://github.com/kev-m/pyCoilGen/blob/master/utilities/CHANGELOG.md
Project-URL: Code of Conduct, https://github.com/kev-m/pyCoilGen/blob/master/CODE_OF_CONDUCT.md
Project-URL: Contributing, https://github.com/kev-m/pyCoilGen/blob/master/CONTRIBUTING.md
Project-URL: Documentation, https://pycoilgen.readthedocs.io/
Project-URL: Home, https://github.com/kev-m/pyCoilGen
Project-URL: Source, https://github.com/kev-m/pyCoilGen/tree/master/utilities
